pdCIFplotter/__init__.py
pdCIFplotter/__main__.py
pdCIFplotter/create_df.py
pdCIFplotter/gui.py
pdCIFplotter/parse_cif.py
pdCIFplotter/plot_cif.py
pdcifplotter-0.1.4.dist-info/AUTHORS.rst
pdcifplotter-0.1.4.dist-info/LICENSE
pdcifplotter-0.1.4.dist-info/METADATA
pdcifplotter-0.1.4.dist-info/WHEEL
pdcifplotter-0.1.4.dist-info/entry_points.txt
pdcifplotter-0.1.4.dist-info/top_level.txt
pdcifplotter-0.1.4.dist-info/RECORD
