Metadata-Version: 2.2
Name: pdCIFplotter
Version: 0.1.4
Summary: A program for visualising diffraction data in pdCIF format.
Home-page: https://github.com/rowlesmr/pdCIFplotter
Author: Matthew Rowles
Author-email: rowlesmr@gmail.com
License: Apache-2.0
Project-URL: Documentation, https://pdcifplotter.readthedocs.io/en/latest/
Project-URL: Changelog, https://pdCIFplotter.readthedocs.io/en/latest/changelog.html
Project-URL: Issue Tracker, https://github.com/rowlesmr/pdCIFplotter/issues
Keywords: diffraction,X-ray,neutron,synchrotron,powder diffraction,CIF,crystallography
Classifier: Development Status :: 4 - Beta
Classifier: Intended Audience :: End Users/Desktop
Classifier: Intended Audience :: Science/Research
Classifier: License :: OSI Approved :: Apache Software License
Classifier: Operating System :: Unix
Classifier: Operating System :: POSIX
Classifier: Operating System :: Microsoft :: Windows
Classifier: Programming Language :: Python :: 3 :: Only
Classifier: Programming Language :: Python :: 3.7
Classifier: Programming Language :: Python :: 3.8
Classifier: Programming Language :: Python :: 3.9
Classifier: Programming Language :: Python :: Implementation :: CPython
Classifier: Topic :: Utilities
Classifier: Topic :: Scientific/Engineering
Requires-Python: >=3.7
License-File: LICENSE
License-File: AUTHORS.rst
Requires-Dist: cycler>=0.11
Requires-Dist: kiwisolver>=1.3
Requires-Dist: matplotlib>=3.4
Requires-Dist: mplcursors>=0.5
Requires-Dist: numpy>=1.21
Requires-Dist: Pillow>=8.4
Requires-Dist: PyCifRW>=4.4.3
Requires-Dist: pyparsing>=3.0
Requires-Dist: FreeSimpleGUI
Requires-Dist: python-dateutil>=2.8
Requires-Dist: six>=1.16
Dynamic: author
Dynamic: author-email
Dynamic: classifier
Dynamic: description
Dynamic: home-page
Dynamic: keywords
Dynamic: license
Dynamic: project-url
Dynamic: requires-dist
Dynamic: requires-python
Dynamic: summary
